{   "id":"0056",
    "nombre" :"Speedfol B SP",
    "presentacion":["1kg","25kg"],
    "descripcionCorta":"Producto Estrella",
    "img":"speedfol-bsp.png",
    "marcaID":"speedfol",
    "marca":"Speedfol",
    "lineaID":"",
    "linea":"B SP",
    "metaTags":["speedfol","boro"],
    "descripcion":"<p> Producto derivado a partir del acido bórico, el cual es la única forma de Boro absorbido por la planta, haciendo de esta la más eficiente fuente de Boro. </p> <p> Formulación de Poliborato con contenido de B de 17% en combinación con su sistema de penetración y antilavado por lluvia, favorecen su solubilidad y absorción por la planta. </p> <p> Es plicado al follaje para mejorar la cuaja y productividad de vegetales, frutos, nueces, cereales y otros cultivos. </p> <p> Su acidez de pH 5 reduce el pH de aguas alcalinas, lo cual hace que Speedfol&reg; B SP sea idealmente propicio para aplicaciones con la mayoría de pesticidas agrícolas por su mayor estabilidad y efectividad. </p>", 
    "informacionTecnica":"<table class='table table-striped'>  <tbody> <tr> <td colspan=\"3\"> <p> Riqueza Porcentual </p> </td> </tr> <tr> <td> <p> Boro </p> </td> <td> <p> B </p> </td> <td> <p> 17 g /L </p> </td> </tr> <tr> <td colspan=\"3\"> <p> Especificaciones de Disolución </p> </td> </tr> <tr> <td> <p> CE (1 g / L a 20º C) </p> </td> <td colspan=\"2\"> <p> 0.1 mS/cm </p> </td> </tr> <tr> <td> <p> pH (1 g / L a 20º C) </p> </td> <td colspan=\"2\"> <p> 5.0 </p> </td> </tr> <tr> <td> <p> Solubilidad (20º C) </p> </td> <td colspan=\"2\"> <p> 60 g/ L </p> </td> </tr> </tbody> </table>",
    "hojaProducto":"<table class='table table-striped table-bordered table-condensed'> <tr> <td> Sin Información.</td> </tr> </table>",
    "informacionBasicaNutrientes":"<div> <table class='table table-striped'>  <tbody> <tr> <td colspan=\"3\"> <p> Riqueza Porcentual </p> </td> </tr> <tr> <td> <p> Boro </p> </td> <td> <p> B </p> </td> <td> <p> 17 g /L </p> </td> </tr> <tr> <td colspan=\"3\"> <p> Especificaciones de Disolución </p> </td> </tr> <tr> <td> <p> CE (1 g / L a 20º C) </p> </td> <td colspan=\"2\"> <p> 0.1 mS/cm </p> </td> </tr> <tr> <td> <p> pH (1 g / L a 20º C) </p> </td> <td colspan=\"2\"> <p> 5.0 </p> </td> </tr> <tr> <td> <p> Solubilidad (20º C) </p> </td> <td colspan=\"2\"> <p> 60 g/ L </p> </td> </tr> </tbody> </table> </div>"}